mat1plot/__init__.py
mat1plot/plot2d.py
mat1plot-0.0.2.dist-info/LICENSE
mat1plot-0.0.2.dist-info/METADATA
mat1plot-0.0.2.dist-info/WHEEL
mat1plot-0.0.2.dist-info/top_level.txt
mat1plot-0.0.2.dist-info/RECORD
