Metadata-Version: 2.1
Name: mat1plot
Version: 0.0.2
Summary: A plotting package for the 01005 Mathematics 1 course at the Technical University of Denmark
Author-email: Christian Mikkelstrup <s194345@student.dtu.dk>, Hans Henrik Hermansen <s194042@student.dtu.dk>
License: BSD License (BSD)
Project-URL: Homepage, https://gitlab.com/mat1dtu/mat1plot
Project-URL: Mathematics 1 homepage, https://01005.compute.dtu.dk/
Classifier: Programming Language :: Python :: 3
Classifier: Programming Language :: Python :: 3.10
Classifier: License :: OSI Approved :: BSD License
Classifier: Operating System :: OS Independent
Classifier: Development Status :: 1 - Planning
Classifier: Intended Audience :: Education
Classifier: Topic :: Education
Classifier: Topic :: Scientific/Engineering :: Mathematics
Requires-Python: >=3.8
License-File: LICENSE
